clslq/__init__.py
clslq/cli.py
clslq/cli_clslq_notion.py
clslq/cli_clslq_pip.py
clslq/cli_clslq_upgrade.py
clslq/cli_clslq_venv.py
clslq/cli_git.py
clslq/cli_notion_backup.py
clslq/clslq_notion_export.py
clslq/clslq_notion_mreport.py
clslq/clslq_notion_report.py
clslq/clslq_notion_wreport.py
clslq/pip.conf
clslq/version.py
clslq/notion/__init__.py
clslq/notion/blocks.py
clslq/notion/databases.py
clslq/notion/pages.py
clslq/notion/searchall.py
clslq/templates/__init__.py
clslq/templates/monthreport.py
clslq/templates/weekreport.py
clslq-1.3.4.dist-info/AUTHORS
clslq-1.3.4.dist-info/License.py
clslq-1.3.4.dist-info/METADATA
clslq-1.3.4.dist-info/WHEEL
clslq-1.3.4.dist-info/entry_points.txt
clslq-1.3.4.dist-info/top_level.txt
clslq-1.3.4.dist-info/RECORD
