Metadata-Version: 2.1
Name: clslq
Version: 1.3.4
Summary: Connard's python library.
Home-page: http://git.lovelacelee.com
Author: Connard.Lee
Author-email: lovelacelee@gmail.com
License: UNKNOWN
Keywords: clslq,clslqutils
Platform: all
Classifier: Development Status :: 5 - Production/Stable
Classifier: Intended Audience :: Developers
Classifier: Operating System :: OS Independent
Classifier: Topic :: Software Development :: Build Tools
Classifier: License :: OSI Approved :: MIT License
Classifier: Programming Language :: Python :: 3
Classifier: Programming Language :: Python :: 3.3
Classifier: Programming Language :: Python :: 3.4
Classifier: Programming Language :: Python :: 3.5
Classifier: Programming Language :: Python :: 3.6
Classifier: Programming Language :: Python :: 3.7
Classifier: Programming Language :: Python :: 3.8
Classifier: Programming Language :: Python :: 3.9
Requires: loguru
Requires-Python: >=3
License-File: License.py
License-File: AUTHORS
Requires-Dist: clspy
Requires-Dist: loguru
Requires-Dist: Click
Requires-Dist: sqlalchemy
Requires-Dist: notion-client
Requires-Dist: openpyxl
Requires-Dist: requests
Requires-Dist: pandas
